BookerMarkdownTool/__init__.py
BookerMarkdownTool/__main__.py
BookerMarkdownTool/account.py
BookerMarkdownTool/align.py
BookerMarkdownTool/ext_pre.py
BookerMarkdownTool/fmt.py
BookerMarkdownTool/mdalign.py
BookerMarkdownTool/misc.py
BookerMarkdownTool/opti.py
BookerMarkdownTool/ren.py
BookerMarkdownTool/split.py
BookerMarkdownTool/summary.py
BookerMarkdownTool/tomd.js
BookerMarkdownTool/tomd.py
BookerMarkdownTool/util.py
BookerMarkdownTool-2023.7.9.1.dist-info/LICENSE
BookerMarkdownTool-2023.7.9.1.dist-info/METADATA
BookerMarkdownTool-2023.7.9.1.dist-info/WHEEL
BookerMarkdownTool-2023.7.9.1.dist-info/entry_points.txt
BookerMarkdownTool-2023.7.9.1.dist-info/top_level.txt
BookerMarkdownTool-2023.7.9.1.dist-info/RECORD
