Metadata-Version: 2.1
Name: BookerMarkdownTool
Version: 2023.7.9.1
Summary: iBooker/ApacheCN 知识库抓取工具
Home-page: https://github.com/apachecn/BookerMarkdownTool
Author: wizardforcel
Author-email: wizard.z@qq.com
Keywords: wiki,知识库,document,文档,crawler,爬虫
Classifier: Development Status :: 4 - Beta
Classifier: Environment :: Console
Classifier: Intended Audience :: Developers
Classifier: Intended Audience :: End Users/Desktop
Classifier: License :: Other/Proprietary License
Classifier: Natural Language :: Chinese (Simplified)
Classifier: Natural Language :: English
Classifier: Operating System :: OS Independent
Classifier: Programming Language :: Python :: 3
Classifier: Programming Language :: Python :: 3 :: Only
Classifier: Programming Language :: Python :: 3.6
Classifier: Programming Language :: Python :: 3.7
Classifier: Topic :: Internet :: WWW/HTTP
Classifier: Topic :: Text Processing :: Markup :: HTML
Classifier: Topic :: Software Development :: Documentation
Classifier: Topic :: Software Development :: Localization
Classifier: Topic :: Utilities
Requires-Python: >=3.6
License-File: LICENSE
Requires-Dist: requests
Requires-Dist: pyquery
Requires-Dist: readability-lxml
Requires-Dist: pyyaml
Requires-Dist: EpubCrawler
Requires-Dist: imgyaso
